sabbaticas_cli.py
sabbaticas-0.0.1.dist-info/LICENSE
sabbaticas-0.0.1.dist-info/METADATA
sabbaticas-0.0.1.dist-info/WHEEL
sabbaticas-0.0.1.dist-info/entry_points.txt
sabbaticas-0.0.1.dist-info/top_level.txt
sabbaticas-0.0.1.dist-info/RECORD
