Metadata-Version: 2.1
Name: sabbaticas
Version: 0.0.1
Summary: sabbaticas - thoughts and methodology in code.
Author-email: Peter Freiberg <peter.freiberg@gmail.com>
License: MIT License
Project-URL: Homepage, https://github.com/sabbaticas/sabbaticas-cli
Project-URL: Repository, https://github.com/sabbaticas/sabbaticas-cli.git
Keywords: analytics,git,appsec,devsecops,software security
Classifier: Development Status :: 3 - Alpha
Classifier: License :: OSI Approved :: MIT License
Classifier: Programming Language :: Python
Requires-Python: >=3.10
License-File: LICENSE
Requires-Dist: Click
Requires-Dist: prettytable
